astro_databricks/__init__.py
astro_databricks/settings.py
astro_databricks/operators/__init__.py
astro_databricks/operators/common.py
astro_databricks/operators/notebook.py
astro_databricks/operators/workflow.py
astro_databricks/plugins/__init__.py
astro_databricks/plugins/plugin.py
astro_provider_databricks-0.3.2.dist-info/METADATA
astro_provider_databricks-0.3.2.dist-info/WHEEL
astro_provider_databricks-0.3.2.dist-info/entry_points.txt
astro_provider_databricks-0.3.2.dist-info/licenses/LICENSE
astro_provider_databricks-0.3.2.dist-info/RECORD
