Metadata-Version: 2.4
Name: astro-provider-databricks
Version: 0.3.2
Summary: Affordable Databricks Workflows in Apache Airflow
Project-URL: Homepage, https://github.com/astronomer/astro-provider-databricks/
Project-URL: Documentation, https://github.com/astronomer/astro-provider-databricks/
Author-email: Astronomer <humans@astronomer.io>
License-Expression: Apache-2.0
License-File: LICENSE
Keywords: airflow,apache-airflow,astronomer,dags
Classifier: Development Status :: 7 - Inactive
Classifier: Framework :: Apache Airflow
Classifier: Framework :: Apache Airflow :: Provider
Classifier: Intended Audience :: Developers
Classifier: License :: OSI Approved :: Apache Software License
Classifier: Operating System :: OS Independent
Classifier: Programming Language :: Python
Classifier: Programming Language :: Python :: 3
Classifier: Programming Language :: Python :: 3.7
Classifier: Programming Language :: Python :: 3.8
Classifier: Programming Language :: Python :: 3.9
Classifier: Programming Language :: Python :: 3.10
Requires-Python: >=3.7
Requires-Dist: apache-airflow-providers-databricks>=6.8.0
Requires-Dist: apache-airflow>=2.7
Provides-Extra: docs
Requires-Dist: pydata-sphinx-theme; extra == 'docs'
Requires-Dist: sphinx; extra == 'docs'
Requires-Dist: sphinx-autobuild; extra == 'docs'
Requires-Dist: sphinx-tabs; extra == 'docs'
Provides-Extra: tests
Requires-Dist: mypy; extra == 'tests'
Requires-Dist: pytest-cov; extra == 'tests'
Requires-Dist: pytest-describe; extra == 'tests'
Requires-Dist: pytest-dotenv; extra == 'tests'
Requires-Dist: pytest-split; extra == 'tests'
Requires-Dist: pytest>=6.0; extra == 'tests'
Requires-Dist: requests-mock; extra == 'tests'
Requires-Dist: sqlalchemy-stubs; extra == 'tests'
Requires-Dist: types-requests; extra == 'tests'
